<?xml version="1.0" encoding="windows-1251" standalone="yes" ?>
<!-- $Id: Cliffs.xml,v 1.2 2004/11/11 11:33:46 den Exp $  -->
<Cliffs>
    <Set
        name="Cliffs32"
        height="32.000"
        basetile="ground_fall"
        toptile="ground_fall"
        cliffscale="1.000 1.000 1.000">
        <Item model="data/models/cliffs/32_grass_1q.sam"		 type="0"/>
        <Item model="data/models/cliffs/32_grass_h_3.sam"	 type="1"/>
        <Item model="data/models/cliffs/32_grass_h_4.sam"	 type="1"/>
        <Item model="data/models/cliffs/32_grass_3q_1.sam"	 type="2"/>
        <Item model="data/models/cliffs/32_grass_3q_2.sam"	 type="2"/>
        <Item model="data/models/cliffs/32_grass_d_1.sam"	 type="3"/>
    </Set>
    <Set
        name="Cliffs16"
        height="16.000"
        basetile="ground_fall"
        toptile="ground_fall"
        cliffscale="1.000 1.000 1.000">
        <Item model="data/models/cliffs/16_grass_1q_3.sam"	 type="0"/>
        <Item model="data/models/cliffs/16_grass_1q_visit_1.sam"	 type="0"/>
        <Item model="data/models/cliffs/16_grass_h_1.sam"	 type="1"/>
        <Item model="data/models/cliffs/16_grass_h_2.sam"	 type="1"/>
        <Item model="data/models/cliffs/16_grass_h_3.sam"	 type="1"/>
        <Item model="data/models/cliffs/16_grass_h_4.sam"	 type="1"/>
        <Item model="data/models/cliffs/16_grass_h_visit_1.sam"	 type="1"/>
        <Item model="data/models/cliffs/16_grass_h_visit_2.sam"	 type="1"/>
        <Item model="data/models/cliffs/16_grass_3q_1.sam"	 type="2"/>
        <Item model="data/models/cliffs/16_grass_3q_2.sam"	 type="2"/>
        <Item model="data/models/cliffs/16_grass_d_1.sam"	 type="3"/>
    </Set>

</Cliffs>